flake8_keyword_function_parameters.py
flake8_keyword_function_parameters-0.1.0.dist-info/LICENSE
flake8_keyword_function_parameters-0.1.0.dist-info/METADATA
flake8_keyword_function_parameters-0.1.0.dist-info/WHEEL
flake8_keyword_function_parameters-0.1.0.dist-info/entry_points.txt
flake8_keyword_function_parameters-0.1.0.dist-info/top_level.txt
flake8_keyword_function_parameters-0.1.0.dist-info/RECORD
