Metadata-Version: 2.1
Name: flake8-keyword-function-parameters
Version: 0.1.0
Summary: Flake8 plugin to lint for keyword-only function parameters
Home-page: https://github.com/asib/flake8_keyword_function_parameters
Author: Jacob Fenton
Author-email: jacob+flake8_keyword_function_parameters@dfenton.xyz
License: MIT
Classifier: License :: OSI Approved :: MIT License
Classifier: Programming Language :: Python :: 3
Classifier: Programming Language :: Python :: 3 :: Only
Classifier: Programming Language :: Python :: 3.7
Classifier: Programming Language :: Python :: 3.8
Classifier: Programming Language :: Python :: 3.9
Classifier: Programming Language :: Python :: 3.10
Classifier: Programming Language :: Python :: 3.11
Requires-Python: >=3.7
License-File: LICENSE
Requires-Dist: flake8 (>=3.7)
Requires-Dist: importlib-metadata (>=0.9) ; python_version < "3.8"
